{
	"name": "iconType",
	"plugin-id": "Sprite",
	"sid": 365097240368774,
	"isGlobal": false,
	"instanceVariables": [
		{
			"name": "I_Select",
			"type": "boolean",
			"desc": "",
			"show": true,
			"sid": 451617140687972
		},
		{
			"name": "I_NameType",
			"type": "string",
			"desc": "",
			"show": true,
			"sid": 573321907218527
		}
	],
	"behaviorTypes": [
		{
			"behaviorId": "Tween",
			"name": "Tween",
			"sid": 958115909599001
		},
		{
			"behaviorId": "Mitsuhashish_ColorVariable",
			"name": "ColorVariable",
			"sid": 471347112780748
		}
	],
	"effectTypes": [
		{
			"effectId": "skymen_BetterOutline",
			"name": "BetterOutline"
		}
	],
	"animations": {
		"items": [
			{
				"frames": [
					{
						"width": 50,
						"height": 50,
						"originX": 0.5,
						"originY": 0.5,
						"originalSource": "",
						"exportFormat": "lossless",
						"exportQuality": 0.8,
						"imageSpriteId": 5295069,
						"collisionPoly": {
							"points": [
								0.34,
								0.02,
								0.46,
								0.02,
								0.8,
								0.14,
								0.98,
								0.44,
								0.98,
								0.58,
								0.96,
								0.78,
								0.94,
								0.82,
								0.88,
								0.88,
								0.82,
								0.92,
								0.7,
								0.98,
								0.56,
								1,
								0.12,
								0.88,
								0,
								0.38,
								0,
								0.28,
								0.02,
								0.22,
								0.06,
								0.14,
								0.12,
								0.08
							]
						},
						"useCollisionPoly": true,
						"duration": 1,
						"tag": ""
					},
					{
						"width": 50,
						"height": 50,
						"originX": 0.5,
						"originY": 0.5,
						"originalSource": "",
						"exportFormat": "lossless",
						"exportQuality": 0.8,
						"imageSpriteId": 9308354,
						"collisionPoly": {
							"points": [
								0.52,
								0.02,
								0.6,
								0.04,
								0.64,
								0.06,
								0.7,
								0.1,
								0.74,
								0.16,
								0.76,
								0.22,
								0.88,
								0.82,
								0.86,
								0.94,
								0.82,
								0.96,
								0.74,
								0.98,
								0.28,
								0.98,
								0.2,
								0.96,
								0.14,
								0.92,
								0.14,
								0.82,
								0.26,
								0.22,
								0.28,
								0.16,
								0.32,
								0.1,
								0.38,
								0.06,
								0.42,
								0.04
							]
						},
						"useCollisionPoly": true,
						"duration": 1,
						"tag": ""
					},
					{
						"width": 50,
						"height": 50,
						"originX": 0.5,
						"originY": 0.5,
						"originalSource": "",
						"exportFormat": "lossless",
						"exportQuality": 0.8,
						"imageSpriteId": 1946299,
						"collisionPoly": {
							"points": [
								0.46,
								0,
								0.6,
								0,
								0.74,
								0.04,
								0.8,
								0.2,
								0.96,
								0.92,
								0.92,
								0.98,
								0.84,
								0.98,
								0.54,
								0.9,
								0.12,
								0.58,
								0.06,
								0.52,
								0.04,
								0.48,
								0.02,
								0.4,
								0.02,
								0.3,
								0.24,
								0.1,
								0.3,
								0.06,
								0.34,
								0.04
							]
						},
						"useCollisionPoly": true,
						"duration": 1,
						"tag": ""
					},
					{
						"width": 50,
						"height": 50,
						"originX": 0.5,
						"originY": 0.5,
						"originalSource": "",
						"exportFormat": "lossless",
						"exportQuality": 0.8,
						"imageSpriteId": 8700549,
						"collisionPoly": {
							"points": [
								0.06,
								0.08,
								0.78,
								0.1,
								0.92,
								0.36,
								0.98,
								0.72,
								0.98,
								0.78,
								0.84,
								0.94,
								0.16,
								0.94,
								0.02,
								0.8,
								0.04,
								0.12
							]
						},
						"useCollisionPoly": true,
						"duration": 1,
						"tag": ""
					},
					{
						"width": 50,
						"height": 50,
						"originX": 0.5,
						"originY": 0.5,
						"originalSource": "",
						"exportFormat": "lossless",
						"exportQuality": 0.8,
						"imageSpriteId": 3674333,
						"collisionPoly": {
							"points": [
								0.48,
								0.08,
								1,
								0.24,
								1,
								0.3,
								0.96,
								0.68,
								0.92,
								0.74,
								0.58,
								0.9,
								0.42,
								0.9,
								0.08,
								0.74,
								0.04,
								0.7,
								0,
								0.3,
								0,
								0.22
							]
						},
						"useCollisionPoly": true,
						"duration": 1,
						"tag": ""
					},
					{
						"width": 50,
						"height": 50,
						"originX": 0.5,
						"originY": 0.5,
						"originalSource": "",
						"exportFormat": "lossless",
						"exportQuality": 0.8,
						"imageSpriteId": 4103625,
						"collisionPoly": {
							"points": [
								0.38,
								0.02,
								0.58,
								0.02,
								0.76,
								0.06,
								0.78,
								0.1,
								0.9,
								0.62,
								0.9,
								0.72,
								0.88,
								0.78,
								0.84,
								0.86,
								0.8,
								0.9,
								0.74,
								0.94,
								0.6,
								0.98,
								0.36,
								0.98,
								0.28,
								0.96,
								0.2,
								0.92,
								0.12,
								0.84,
								0.08,
								0.76,
								0.08,
								0.58,
								0.22,
								0.06
							]
						},
						"useCollisionPoly": true,
						"duration": 1,
						"tag": ""
					},
					{
						"width": 50,
						"height": 50,
						"originX": 0.5,
						"originY": 0.5,
						"originalSource": "",
						"exportFormat": "lossless",
						"exportQuality": 0.8,
						"imageSpriteId": 553024,
						"collisionPoly": {
							"points": [
								0.82,
								0,
								0.88,
								0,
								0.92,
								0.04,
								0.92,
								0.12,
								0.84,
								0.74,
								0.8,
								0.78,
								0.76,
								0.8,
								0.24,
								1,
								0.2,
								1,
								0.14,
								0.96,
								0.04,
								0.86,
								0.02,
								0.8,
								0.14,
								0.28,
								0.16,
								0.22,
								0.22,
								0.16
							]
						},
						"useCollisionPoly": true,
						"duration": 1,
						"tag": ""
					}
				],
				"sid": 283508160320219,
				"name": "action",
				"isLooping": false,
				"isPingPong": false,
				"repeatCount": 1,
				"repeatTo": 0,
				"speed": 0
			}
		],
		"subfolders": []
	}
}